pyjudilibre/__init__.py
pyjudilibre/decorators.py
pyjudilibre/enums.py
pyjudilibre/exceptions.py
pyjudilibre/models.py
pyjudilibre/py.typed
pyjudilibre/pyjudilibre.py
pyjudilibre-0.13.1.dist-info/METADATA
pyjudilibre-0.13.1.dist-info/WHEEL
pyjudilibre-0.13.1.dist-info/licenses/LICENSE
pyjudilibre-0.13.1.dist-info/RECORD
