Metadata-Version: 2.4
Name: pyjudilibre
Version: 0.13.1
Summary: Python client for the JUDILIBRE public API
Project-URL: Homepage, https://github.com/pauldechorgnat/pyjudilibre
Project-URL: Issues, https://github.com/pauldechorgnat/pyjudilibre/issues
Author-email: Paul <you@example.com>
License: MIT License
License-File: LICENSE
Requires-Python: >=3.9
Requires-Dist: httpx==0.28.1
Requires-Dist: pydantic>=2.10.2
Requires-Dist: tqdm==4.67.1
Provides-Extra: build
Requires-Dist: build; extra == 'build'
Requires-Dist: twine<=6.0.1; extra == 'build'
Provides-Extra: dev
Requires-Dist: bump-my-version==1.2.4; extra == 'dev'
Requires-Dist: isort==6.0.1; extra == 'dev'
Requires-Dist: jupyterlab==4.4.5; extra == 'dev'
Requires-Dist: mypy>=1.17.1; extra == 'dev'
Requires-Dist: ruff==0.12.8; extra == 'dev'
Provides-Extra: doc
Requires-Dist: mkdocs-material>=9.6.16; extra == 'doc'
Requires-Dist: mkdocs>=1.6.1; extra == 'doc'
Requires-Dist: mkdocstrings-python>=1.16.12; extra == 'doc'
Provides-Extra: test
Requires-Dist: pytest==8.4.1; extra == 'test'
Requires-Dist: python-dotenv==1.1.1; extra == 'test'
